AUTHOR
LICENSE
MANIFEST.in
README.rst
setup.cfg
setup.py
doc/source/_static/pydcmio.png
doc/source/_static/carousel/dti.png
doc/source/_static/carousel/t2.png
pyDcmio.egg-info/PKG-INFO
pyDcmio.egg-info/SOURCES.txt
pyDcmio.egg-info/dependency_links.txt
pyDcmio.egg-info/requires.txt
pyDcmio.egg-info/top_level.txt
pydcmio/__init__.py
pydcmio/info.py
pydcmio/dcm2nii/__init__.py
pydcmio/dcm2nii/exceptions.py
pydcmio/dcm2nii/wrapper.py
pydcmio/dcmanonymizer/__init__.py
pydcmio/dcmanonymizer/anonymize.py
pydcmio/dcmanonymizer/callbacks.py
pydcmio/dcmanonymizer/deidentify.json
pydcmio/dcmanonymizer/private_deidentify.json
pydcmio/dcmanonymizer/utils.py
pydcmio/dcmconverter/__init__.py
pydcmio/dcmconverter/converter.py
pydcmio/dcmconverter/spliter.py
pydcmio/dcmconverter/transcoder.py
pydcmio/dcmreader/__init__.py
pydcmio/dcmreader/csa2.py
pydcmio/dcmreader/reader.py
pydcmio/dcmreader/rtstruct.py
pydcmio/deface/__init__.py
pydcmio/deface/mask_face.py
pydcmio/deface/mri_deface.py
pydcmio/deface/pdeface.py
pydcmio/plotting/__init__.py
pydcmio/plotting/slicer.py
pydcmio/scripts/pydcmio_deface_post
pydcmio/scripts/pydcmio_deface_pre
pydcmio/scripts/pydcmio_dicom2nifti
pydcmio/scripts/pydcmio_dicomanonymizer
pydcmio/scripts/pydcmio_dicomreader
pydcmio/scripts/pydcmio_maskface
pydcmio/scripts/pydcmio_nifti2dicom
pydcmio/scripts/pydcmio_rtstruct
pydcmio/scripts/pydcmio_splitseries
pydcmio/scripts/pydcmio_transcode