Metadata-Version: 1.1
Name: pyDcmio
Version: 2.0.2
Summary: 
